htmlgen/__init__.py
htmlgen/__init__.pyi
htmlgen/attribute.py
htmlgen/attribute.pyi
htmlgen/block.py
htmlgen/block.pyi
htmlgen/document.py
htmlgen/document.pyi
htmlgen/element.py
htmlgen/element.pyi
htmlgen/form.py
htmlgen/form.pyi
htmlgen/generator.py
htmlgen/generator.pyi
htmlgen/image.py
htmlgen/image.pyi
htmlgen/inline.py
htmlgen/inline.pyi
htmlgen/link.py
htmlgen/link.pyi
htmlgen/list.py
htmlgen/list.pyi
htmlgen/py.typed
htmlgen/structure.py
htmlgen/structure.pyi
htmlgen/table.py
htmlgen/table.pyi
htmlgen/time.py
htmlgen/time.pyi
htmlgen/timeutil.py
htmlgen/timeutil.pyi
htmlgen-1.2.1.dist-info/METADATA
htmlgen-1.2.1.dist-info/RECORD
htmlgen-1.2.1.dist-info/WHEEL
htmlgen-1.2.1.dist-info/top_level.txt
test_htmlgen/__init__.py
test_htmlgen/attribute.py
test_htmlgen/block.py
test_htmlgen/document.py
test_htmlgen/element.py
test_htmlgen/form.py
test_htmlgen/generator.py
test_htmlgen/image.py
test_htmlgen/inline.py
test_htmlgen/link.py
test_htmlgen/list.py
test_htmlgen/structure.py
test_htmlgen/table.py
test_htmlgen/time.py
test_htmlgen/util.py
